pyrosim/__init__.py
pyrosim/clients.py
pyrosim/locations.py
pyrosim/vehicles.py
pyrosim-0.0.4.dist-info/LICENSE
pyrosim-0.0.4.dist-info/METADATA
pyrosim-0.0.4.dist-info/WHEEL
pyrosim-0.0.4.dist-info/top_level.txt
pyrosim-0.0.4.dist-info/RECORD
